{
  "version": 14,
  "mainLocations": [
    "Quest_Global_TheHunterDream_Template01",
    "Quest_Story_AllFather_DranCity1_Template",
    "Quest_Story_AllFather_DranCity2_Template",
    "Quest_Story_Empress_Zone01_Template01",
    "Quest_Story_Empress_Zone02_Template01",
    "Quest_Story_IAmLegend_Zone1_Template",
    "Quest_Story_IAmLegend_Zone2_Template"
  ],
  "subLocations": {
    "Jungle": {
      "Shrewd": "The Expanding Glade",
      "RavagerStory": "Ravager's Lair",
      "RootHorror": "Kaeula's Rest",
      "RootCultist": "The Twisted Chantry",
      "MotherMind": "The Nameless Nest",
      "Meidra": "The Dappled Glade",
      "Ruins": "Abandoned Ruins",
      "KoaraKuri": "Koara Kuri Nest",
      "HiddenMaze": "Endaira's End",
      "TheTangle": "Imperial Gardens",
      "TheLament": "The Lament",
      "Sarcophagus": "The Lament",
      "TheChimney": "Laemir's Lyceum",
      "WailingField": "Forgotten Field",
      "CathedralOfSeasons": "Cathedral Of Seasons",
      "Empress": "The Red Throne",
      "ManyFaces": "The Great Bole"
    },
    "Fae": {
      "AllFather": "Beatific Palace",
      "DranGrenadier": "Cotton's Kiln",
      "Ravenous": "The Great Hall",
      "CharnelHouse": "Harvester's Reach",
      "TheHunter": "Briella's Garden",
      "BloatKing": "The Great Sewers",
      "CrimsonHarvest": "Butcher's Quarter",
      "FaeArchon": "Shattered Gallery",
      "FaeCouncil": "Council Chamber",
      "RedPrince": "Gilded Chambers",
      "DranOracle": "Oracle'' sRefuge",
      "Settlement": "Bairn's Crossing",
      "Nimue": "Nimue's Retreat",
      "FaelinFaerlin": "Beatific Palace",
      "Faerin": "Malefic Gallery",
      "__TheNest": "Sewers",
      "TownTurnedToDust": "Tiller's Rest",
      "ThreeMenMorris": "Postulant's Parlor"
    },
    "Nerud": {
      "Abomination": "The Putrid Domain",
      "Hatchery": "The Hatchery",
      "Extraction": "Dark Conduit",
      "Extermination": "Dormant N'Erudian Facility",
      "Train": "Terminus Station",
      "CustodianEye": "Spectrum Nexus",
      "TowerHeist": "Tower Of The Unseen",
      "TheDreamlessSleep": "Void Vessel Facility",
      "NerudGuardian": "Threshold Of The Unknown",
      "TheCustodian": "The Phantom Wasteland",
      "TalRatha": "Forgotten Prison",
      "Phantom": "Astropath's Respite",
      "StasisSiege": "Vault Of The Formless"
    }
  },
  "injectableParents": {
    "HiddenChamber": "HiddenMaze"
  },
  "injectables": {
    "Jungle": {
      "TheChimney": "Crypt",
      "TheLament": "Crypt",
      "RootCultist": "Crypt",
      "LivingStone": "Crypt",
      "Sarcophagus": "Crypt",
      "CryptHidden": "Crypt",
      "TheTangle": "Island",
      "WailingField": "Island",
      "Shrewd": "Island",
      "MotherMind": "Island",
      "BrokenTomb": "Island",
      "Tower": "Island",
      "IslandJump": "Island",
      "CathedralOfSeasons": "Ziggurat",
      "RootHorror": "Ziggurat",
      "HiddenMaze": "Ziggurat",
      "HiddenChamber": "Ziggurat",
      "Library": "Ziggurat",
      "WindHollow": "Ziggurat"
    },
    "Nerud": {
      "TowerHeist": "Tower",
      "ElevatorShaft": "Tower",
      "RemainsBelow": "Tower",
      "Seeker": "Tower",
      "BlackHole": "Underworld",
      "LurkerVents": "Underworld",
      "SewageFacility": "Underworld",
      "Shockwire": "Underworld",
      "StoreRoom": "Underworld",
      "TheClaw": "Underworld"
    }
  },
  "events": {
    "Jungle": {
      "Fester": [
        {
          "name": "/Items/Gems/Melee/MetaGems/VampireBlade/MetaGem_VampireBlade"
        }
      ],
      "Wither": [
        {
          "name": "/Items/Gems/Melee/MetaGems/Overdrive/MetaGem_Overdrive"
        }
      ],
      "Amulet_ScavengersBauble": [
        {
          "name": "/Items/Trinkets/Amulets/ScavengersBauble/Amulet_ScavengersBauble"
        }
      ],
      "Amulet_StalkersBrand": [
        {
          "name": "/Items/Trinkets/Amulets/StalkersBrand/Amulet_StalkersBrand"
        }
      ],
      "Amulet_VengeanceIdol": [
        {
          "name": "/Items/Trinkets/Amulets/VengeanceIdol/Amulet_VengeanceIdol"
        }
      ],
      "Ring_BloodStamp": [
        {
          "name": "/Items/Trinkets/Rings/WaxSealedRing/Ring_WaxSealedRing"
        }
      ],
      "Ring_CelerityStone": [
        {
          "name": "/Items/Trinkets/Rings/CelerityStone/Ring_CelerityStone"
        }
      ],
      "Ring_VestigeOfPower": [
        {
          "name": "/Items/Trinkets/Rings/VestigeOfPower/Ring_VestigeOfPower"
        }
      ],
      "Ring_GuardiansRing": [
        {
          "name": "/Items/Trinkets/Rings/GuardiansRing/Ring_GuardiansRing"
        }
      ],
      "Ring_HeartOfTheWolf": [
        {
          "name": "/Items/Trinkets/Rings/HeartOfTheWolf/Ring_HeartOfTheWolf"
        }
      ],
      "Ring_RingOfTheForestSpirit": [
        {
          "name": "/Items/Trinkets/Rings/RingOfTheForestSpirit/Ring_RingOfTheForestSpirit"
        }
      ],
      "Ring_Sagestone": [
        {
          "name": "/Items/Trinkets/Rings/SageStone/Ring_Sagestone"
        }
      ],
      "Ring_SoulLink": [
        {
          "name": "/Items/Trinkets/Rings/SoulLink/Ring_SoulLink"
        }
      ],
      "Ring_SpiritStone": [
        {
          "name": "/Items/Trinkets/Rings/SpiritStone/Ring_SpiritStone"
        }
      ],
      "Ring_StoneOfBalance": [
        {
          "name": "/Items/Trinkets/Rings/StoneofBalance/Ring_StoneOfBalance"
        }
      ],
      "Ring_StrongArmBand": [
        {
          "name": "/Items/Trinkets/Rings/StrongArmBand/Ring_StrongArmBand"
        }
      ],
      "LivingStone": [
        {
          "name": "/Items/Trinkets/Rings/LithicSignet/Ring_LithicSignet",
          "notes": "Found in The Lament, The Twisted Chantry, or The Chimney locations on Yaesha at the end of a hidden passageway. To open the passageway, locate a room with 4 statues of Pan Warriors and shoot the crystals in their foreheads, opening a hidden stair case in the middle of the room."
        }
      ],
      "ThaenLeaf": [
        {
          "name": "/Items/Materials/World/ThaenLeaf/Material_ThaenLeaf",
          "ignore": true
        }
      ],
      "EmpressStory": [
        {
          "name": "/Items/Weapons/Melee/Standard/GreatSword/RoyalBroadsword/Weapon_RoyalBroadsword"
        },
        {
          "name": "/Items/Weapons/LongGuns/Standard/Shotgun/Weapon_Shotgun"
        },
        {
          "name": "/Items/Trinkets/Rings/SealOfTheEmpress/Ring_SealOfTheEmpress"
        },
        {
          "name": "/Items/Trinkets/Amulets/MatriarchsInsignia/Amulet_MatriarchsInsignia"
        },
        {
          "name": "/Items/Trinkets/Amulets/RedDoeSigil/Amulet_RedDoeSigil",
          "notes": "Awarded after giving the Ornate Lockbox item (unopened) found in The Widow's Court location on Yaesha, to The Eternal Empress at the Red Throne location on Yaesha."
        },
        {
          "name": "/Items/Trinkets/Rings/ZoheesRing/Ring_ZoheesRing"
        },
        {
          "name": "/Items/Trinkets/Rings/BurdenoftheRebel/Ring_BurdenOfTheRebel"
        }
      ],
      "RavagerStory": [
        {
          "name": "/Items/Trinkets/Rings/FrivolousBand/Ring_FrivolousBand"
        },
        {
          "name": "/Items/Trinkets/Rings/LodestoneRing/Ring_LodestoneRing",
          "notes": "Awarded from speaking with Bedel of The Vaunnt in the Forbidden Grove location on Yaesha while wearing the Lodestone Crown armor piece."
        },
        {
          "name": "/Items/Trinkets/Rings/BloodJewel/Ring_BloodJewel"
        },
        {
          "name": "/Items/Mods/Mod_SongOfTheEafir/Mod_SongOfEafir"
        },
        {
          "name": "/Items/Weapons/HandGuns/Standard/BoltDriver/Weapon_BoltDriver"
        },
        {
          "name": "/Items/Armor/Base/RelicTesting/LifelessHeart/Relic_Consumable_LifelessHeart"
        }
      ],
      "Ravager": [
        {
          "name": "/Items/Trinkets/Amulets/RavagersMark/Amulet_RavagersMark"
        },
        {
          "name": "/Items/Weapons/Melee/Special/FeralJudgment/Weapon_FeralJudgment",
          "notes": "Crafted by McCabe at Ward 13. Requires the Ravager's Maw item, obtained from performing an Alt Kill on the Corrupted Ravager boss in the Ravager's Lair location on Yaesha. The Alt Kill is performed by shooting the Ravager to initate the fight, killing the Red Doe before the Ravager is able to eat it, and then killing the Ravager boss."
        },
        {
          "name": "/Items/Weapons/Melee/Special/RedDoeStaff/Weapon_RedDoeStaff"
        },
        {
          "name": "/Items/Weapons/LongGuns/Special/Merciless/Weapon_Merciless"
        }
      ],
      "ManyFaces": [
        {
          "name": "/Items/Weapons/LongGuns/Special/TwistedArbalest/Weapon_TwistedArbalest"
        },
        {
          "name": "/Items/Weapons/Melee/Special/Stonebreaker/Weapon_Stonebreaker"
        }
      ],
      "Sarcophagus": [
        {
          "name": "/Items/Gems/Ranged/MetaGems/Extender/MetaGem_Extender"
        }
      ],
      "CryptHidden": [
        {
          "name": "/Items/Trinkets/Rings/TombDwellersRing/Ring_TombDwellersRing"
        },
        {
          "name": "/Items/Trinkets/Amulets/NecklaceOfFlowingLife/Amulet_NecklaceOfFlowingLife"
        }
      ],
      "BrokenTomb": [
        {
          "name": "/Items/Trinkets/Rings/HardenedCoil/Ring_HardenedCoil"
        },
        {
          "name": "/Items/Gems/Ranged/MetaGems/Bandit/MetaGem_Bandit"
        }
      ],
      "IslandJump": [
        {
          "name": "/Items/Trinkets/Amulets/TalismanOfTheSun/Amulet_TalismanOfTheSun"
        }
      ],
      "Tower": [
        {
          "name": "/Items/Trinkets/Rings/SlayersCrest/Ring_SlayersCrest"
        },
        {
          "name": "/Items/Armor/Base/RelicTesting/BloomingHeart/Relic_Consumable_BloomingHeart"
        }
      ],
      "PanRootNexus": [
        {
          "name": "/Items/Trinkets/Amulets/HallowedEgg/Amulet_HallowedEgg"
        }
      ],
      "WindHollow": [
        {
          "name": "/Items/Trinkets/Rings/WindHollowCirclet/Ring_WindHollowCirclet"
        },
        {
          "name": "/Items/Trinkets/Rings/BandBand/Ring_BandBand",
          "coop": true
        }
      ],
      "Library": [
        {
          "name": "/Items/Gems/Ranged/MetaGems/Bulletweaver/MetaGem_Bulletweaver"
        },
        {
          "name": "/Items/Trinkets/Rings/BurdenOfTheFollower/Ring_BurdenOfTheFollower"
        }
      ],
      "MotherMind": [
        {
          "name": "/Items/Mods/Mod_Tremor/Mod_Tremor"
        }
      ],
      "RootCultist": [
        {
          "name": "/Items/Mods/Mod_Fargazer/Mod_Fargazer"
        }
      ],
      "RootHorror": [
        {
          "name": "/Items/Trinkets/Rings/TearOfKaeula/Ring_TearOfKaeula",
          "notes": "Found in the Kaeula's Rest location on Yaesha, at the foot of a statue, beneath a waterfall."
        },
        {
          "name": "/Items/Mods/Mod_Rootlash/Mod_Rootlash"
        }
      ],
      "Shrewd": [
        {
          "name": "/Items/Mods/Mod_RottedArrow/Mod_RottedArrow"
        }
      ],
      "Amulet_DeathsEmbrace": [
        {
          "name": "/Items/Trinkets/Amulets/DeathsEmbrace/Amulet_DeathsEmbrace"
        }
      ],
      "BloodMoon": [
        {
          "name": "/Items/Weapons/Melee/Standard/Sword/BladeOfGul/Weapon_BladeOfGul"
        },
        {
          "name": "/Items/Armor/Archetype/Summoner/Armor_Head_Summoner"
        },
        {
          "name": "/Items/Armor/Archetype/Summoner/Armor_Body_Summoner"
        },
        {
          "name": "/Items/Armor/Archetype/Summoner/Armor_Legs_Summoner"
        },
        {
          "name": "/Items/Armor/Archetype/Summoner/Armor_Gloves_Summoner"
        },
        {
          "name": "/Items/Materials/Engrams/Item_HiddenContainer_Material_Engram_Summoner"
        },
        {
          "name": "/Items/Trinkets/Amulets/SoulAnchor/Amulet_SoulAnchor"
        }
      ],
      "Meidra": [
        {
          "name": "/Items/Weapons/HandGuns/Special/Sorrow/Weapon_Sorrow"
        },
        {
          "name": "/Items/Traits/Core/Barkskin/Trait_Barkskin"
        },
        {
          "name": "/Items/Traits/Core/Bloodstream/Trait_Bloodstream"
        }
      ],
      "Flautist": [
        {
          "name": "/Items/Trinkets/Amulets/HallowedEgg/Amulet_HallowedEgg"
        },
        {
          "name": "/Items/Traits/Core/BloodBond/Trait_BloodBond"
        }
      ],
      "Amulet_KoaraKuri": [
        {
          "name": "/Items/Trinkets/Amulets/KuriKuriCharm/Amulet_KuriKuriCharm"
        }
      ],
      "CathedralOfSeasons": [
        {
          "name": "/Items/Mods/Mod_AstralBurst/Mod_AstralBurst"
        },
        {
          "name": "/Items/Trinkets/Rings/RingOfOmens/Ring_RingOfOmens",
          "notes": "Found in the Cathedral of Omens location on Yaesha, behind a red trap door on the ground, after solving the Blood Moon puzzle. The trapdoor will only open during the Blood Moon event."
        },
        {
          "name": "/Items/Weapons/LongGuns/Special/Sagittarius/Weapon_Sagittarius"
        }
      ],
      "HiddenMaze": [
        {
          "name": "/Items/Trinkets/Rings/TempestConduit/Ring_TempestConduit"
        },
        {
          "name": "/Items/Trinkets/Rings/CaptainsInsignia/Ring_CaptainsInsignia",
          "coop": true
        },
        {
          "name": "/Items/Trinkets/Rings/EndairasEndlessLoop/Ring_EndairasEndlessLoop"
        },
        {
          "name": "/Items/Weapons/Melee/Standard/Hatchet/KrellAxe/Weapon_KrellAxe"
        },
        {
          "name": "/Items/Armor/Base/RelicTesting/PulsingHeart/Relic_Consumable_PulsingHeart"
        }
      ],
      "HiddenChamber": [
        {
          "name": "/Items/Trinkets/Rings/ArchersCrest/Ring_ArchersCrest"
        }
      ],
      "TheChimney": [
        {
          "name": "/Items/Mods/Mod_Soulbinder/Mod_Soulbinder"
        },
        {
          "name": "/Items/Trinkets/Amulets/DownwardSpiral/Amulet_DownwardSpiral",
          "notes": "Found in the Chimney location on Yaesha, hidden halfway down the staircase in the Crystal Elevator event."
        }
      ],
      "TheLament": [
        {
          "name": "/Items/Armor/Armor_Head_LodestoneCrown",
          "notes": "On the boat inside Kolkets locked room"
        },
        {
          "name": "/Items/Trinkets/Rings/BloodTingedRing/Ring_BloodTingedRing"
        },
        {
          "name": "/Items/Trinkets/Rings/RingOfDiversion/Ring_RingOfDiversion"
        },
        {
          "name": "/Items/Armor/RedWidow/Armor_Head_RedWidow"
        },
        {
          "name": "/Items/Armor/RedWidow/Armor_Body_RedWidow"
        },
        {
          "name": "/Items/Armor/RedWidow/Armor_Legs_RedWidow"
        },
        {
          "name": "/Items/Armor/RedWidow/Armor_Gloves_RedWidow"
        }
      ],
      "TheTangle": [
        {
          "name": "/Items/Trinkets/Amulets/FullMoonCirclet/Amulet_FullMoonCirclet",
          "notes": "Found in The Imperial Gardens location on Yaesha, in a hidden room below a trapdoor marked with a golden full moon crest. The trapdoor will only open during the Blood Moon event."
        },
        {
          "name": "/Items/Weapons/Melee/Standard/Katana/EdgeOfTheForest/Weapon_EdgeOfTheForest"
        },
        {
          "name": "/Items/Weapons/LongGuns/Standard/Crossbow/Weapon_Crossbow"
        }
      ],
      "Mantagora": [
        {
          "name": "/Items/Gems/Ranged/MetaGems/Momentum/MetaGem_Momentum"
        }
      ],
      "WailingField": [
        {
          "name": "/Items/Trinkets/Amulets/LaemirCenser/Amulet_LaemirCenser"
        },
        {
          "name": "/Items/Trinkets/Amulets/NecklaceOfSumpremacy/Amulet_NecklaceOfSupremacy"
        },
        {
          "name": "/Items/Gems/Melee/MetaGems/Reinvigorate/MetaGem_Reinvigorate"
        },
        {
          "name": "/Items/Traits/Core/Rugged/Trait_Rugged"
        }
      ],
      "RedDoeStatue": [
        {
          "name": "/Items/Gems/Ranged/MetaGems/GhostShell/MetaGem_GhostShell"
        }
      ]
    },
    "Fae": {
      "Oink": [
        {
          "name": "/Items/Gems/Ranged/MetaGems/TwistingWounds/MetaGem_TwistingWounds"
        }
      ],
      "AsylumChainsaw": [
        {
          "name": "/Items/Gems/Melee/MetaGems/Striker/MetaGem_Striker"
        }
      ],
      "CharnelHouse": [
        {
          "name": "/Items/Gems/Ranged/MetaGems/Lithely/MetaGem_Lithely"
        },
        {
          "name": "/Items/Trinkets/Rings/RingOfRetribution/Ring_RingOfRetribution"
        },
        {
          "name": "/Items/Trinkets/Rings/RingOfGrace/Ring_RingOfGrace",
          "notes": "Give Dria's Anklet to Riewen'"
        },
        {
          "name": "/Items/Traits/Core/ArcaneStrike/Trait_ArcaneStrike"
        }
      ],
      "AboveBelow": [
        {
          "name": "/Items/Gems/Melee/MetaGems/Steadfast/MetaGem_Steadfast"
        },
        {
          "name": "/Items/Weapons/Melee/Standard/Flail/OrnateFlail/Weapon_OrnateFlail"
        },
        {
          "name": "/Items/Trinkets/Rings/SapphireDreamstone/Ring_SapphireDreamstone"
        }
      ],
      "Ring_AlchemyStone": [
        {
          "name": "/Items/Trinkets/Rings/AlchemyStone/Ring_AlchemyStone"
        }
      ],
      "Ring_AlumniRing": [
        {
          "name": "/Items/Trinkets/Rings/AlumniRing/Ring_AlumniRing"
        }
      ],
      "Ring_BoosterRing": [
        {
          "name": "/Items/Trinkets/Rings/BoosterRing/Ring_BoosterRing"
        }
      ],
      "Ring_BurdenOfTheDivine": [
        {
          "name": "/Items/Trinkets/Rings/BurdenOfTheDivine/Ring_BurdenOfTheDivine"
        }
      ],
      "Ring_BurdenOfTheWarlock": [
        {
          "name": "/Items/Trinkets/Rings/BurdenOfTheWarlock/Ring_BurdenOfTheWarlock"
        }
      ],
      "Ring_CatalogersJewel": [
        {
          "name": "/Items/Trinkets/Rings/CatalogersJewel/Ring_CatalogersJewel"
        }
      ],
      "Ring_DranMemento": [
        {
          "name": "/Items/Trinkets/Rings/DranMemento/Ring_DranMemento"
        }
      ],
      "Ring_FaeShamanRing": [
        {
          "name": "/Items/Trinkets/Rings/DranShamanRing/Ring_FaeShamanRing"
        }
      ],
      "Ring_FaeBruiserRing": [
        {
          "name": "/Items/Trinkets/Rings/FaeBruiserRing/Ring_FaeBruiserRing"
        }
      ],
      "Ring_FaeHunterRing": [
        {
          "name": "/Items/Trinkets/Rings/FaeHunterRing/Ring_FaeHunterRing"
        }
      ],
      "Ring_FaeProtectorSignet": [
        {
          "name": "/Items/Trinkets/Rings/FaeProtectorSignet/Ring_FaeProtectorSignet"
        }
      ],
      "Ring_FaeWarriorRing": [
        {
          "name": "/Items/Trinkets/Rings/FaeWarriorRing/Ring_FaeWarriorRing"
        }
      ],
      "Ring_FeastmastersSignet": [
        {
          "name": "/Items/Trinkets/Rings/FeastmastersSignet/Ring_FeastmastersSignet"
        }
      ],
      "Ring_FireStone": [
        {
          "name": "/Items/Trinkets/Rings/FireStone/Ring_FireStone"
        }
      ],
      "Ring_GroundingStone": [
        {
          "name": "/Items/Trinkets/Rings/GroundingStone/Ring_GroundingStone"
        }
      ],
      "Ring_OutcastRing": [
        {
          "name": "/Items/Trinkets/Rings/OutcastRing/Ring_OutcastRing"
        }
      ],
      "Ring_RingOfGrace": [
        {
          "name": "/Items/Trinkets/Rings/RingOfGrace/Ring_RingOfGrace"
        }
      ],
      "Ring_RingOfRetribution": [
        {
          "name": "/Items/Trinkets/Rings/RingOfRetribution/Ring_RingOfRetribution"
        }
      ],
      "Ring_RingOfTheRobust": [
        {
          "name": "/Items/Trinkets/Rings/RingOfTheRobust/Ring_RingOfTheRobust"
        }
      ],
      "Ring_ShinyHogLure": [
        {
          "name": "/Items/Trinkets/Rings/ShinyHogLure/Ring_ShinyHogLure"
        }
      ],
      "Ring_StoneOfMalevolence": [
        {
          "name": "/Items/Trinkets/Rings/StoneOfMalevolence/Ring_StoneOfMalevolence"
        }
      ],
      "Ring_DreadFont": [
        {
          "name": "/Items/Trinkets/Rings/DreadFont/Ring_DreadFont"
        }
      ],
      "Ring_StreamCoupler": [
        {
          "name": "/Items/Trinkets/Rings/StreamCoupler/Ring_StreamCoupler"
        }
      ],
      "Amulet_WeightlessWeight": [
        {
          "name": "/Items/Trinkets/Amulets/WeightlessWeight/Amulet_WeightlessWeight"
        }
      ],
      "Amulet_ChainsOfAmplification": [
        {
          "name": "/Items/Trinkets/Amulets/ChainsOfAmplification/Amulet_ChainsOfAmplification"
        }
      ],
      "Amulet_ConductivePadding": [
        {
          "name": "/Items/Trinkets/Amulets/ConductivePadding/Amulet_ShockDevice"
        }
      ],
      "Amulet_JestersBell": [
        {
          "name": "/Items/Trinkets/Amulets/JestersBell/Amulet_JestersBell"
        }
      ],
      "Amulet_NeckboneNecklace": [
        {
          "name": "/Items/Trinkets/Amulets/NeckboneNecklace/Amulet_NeckboneNecklace"
        }
      ],
      "Amulet_IndignantFetish": [
        {
          "name": "/Items/Trinkets/Amulets/IndignantFetish/Amulet_IndignantFetish"
        }
      ],
      "Amulet_SpiritWispAmulet": [
        {
          "name": "/Items/Trinkets/Amulets/SpiritWispAmulet/Amulet_SpiritWispAmulet"
        }
      ],
      "Nimue": [
        {
          "name": "/Items/Trinkets/Rings/HexWard/Ring_HexWard"
        },
        {
          "name": "/Items/Trinkets/Amulets/OneTrueKingSigil/Amulet_OneTrueKingSigil",
          "notes": "Give Faerin and Faelin's Sigil to Nimue"
        },
        {
          "name": "/Items/Trinkets/Amulets/NimuesRibbon/Amulet_NimuesRibbon",
          "notes": "Give Silver and Gold Ribbon to Nimue"
        },
        {
          "name": "/Items/Weapons/Melee/Standard/Sword/AssassinsDagger/Weapon_AssassinsDagger",
          "notes": "Give Council Chambers dagger to Nimue"
        },
        {
          "name": "/Items/Weapons/LongGuns/Special/CrescentMoon/Weapon_CrescentMoon",
          "notes": "Use Dreamcatcher on Nimue while she is sleeping"
        },
        {
          "name": "/Items/Armor/Base/RelicTesting/TranquilHeart/Relic_Consumable_TranquilHeart",
          "notes": "Give Tormented Heart to Nimue"
        }
      ],
      "BoneHarvesterLair": [
        {
          "name": "/Items/Trinkets/Rings/DrakestonePearl/Ring_DrakestonePearl",
          "tileSet": "Fae_Sewer_End_HarvesterLair"
        },
        {
          "name": "/Items/Materials/Engrams/Item_HiddenContainer_Material_Engram_Alchemist",
          "tileSet": "City_End_HarvesterLair"
        },
        {
          "name": "/Items/Armor/Archetype/Alchemist/Armor_Head_Alchemist",
          "tileSet": "Fae_Sewer_End_HarvesterLair"
        },
        {
          "name": "/Items/Armor/Archetype/Alchemist/Armor_Body_Alchemist",
          "tileSet": "Fae_Sewer_End_HarvesterLair"
        },
        {
          "name": "/Items/Armor/Archetype/Alchemist/Armor_Legs_Alchemist",
          "tileSet": "Fae_Sewer_End_HarvesterLair"
        },
        {
          "name": "/Items/Armor/Archetype/Alchemist/Armor_Gloves_Alchemist",
          "tileSet": "Fae_Sewer_End_HarvesterLair"
        }
      ],
      "CrimsonHarvest": [
        {
          "name": "/Items/Traits/Core/Shadeskin/Trait_Shadeskin"
        },
        {
          "name": "/Items/Trinkets/Rings/DranMemento/Ring_DranMemento"
        },
        {
          "name": "/Items/Trinkets/Rings/SingedRing/Ring_SingedRing"
        }
      ],
      "BloatKing": [
        {
          "name": "/Items/Mods/Mod_VoltaicRondure/Mod_VoltaicRondure"
        }
      ],
      "BlackAndWhite": [
        {
          "name": "/Items/Trinkets/Rings/BlackPawnStamp/Ring_BlackPawnStamp"
        },
        {
          "name": "/Items/Trinkets/Rings/WhitePawnStamp/Ring_WhitePawnStamp"
        }
      ],
      "TheNest": [
        {
          "name": "/Items/Trinkets/Rings/StockpileDelayLoop/Ring_StockpileCharger"
        }
      ],
      "Ravenous": [
        {
          "name": "/Items/Weapons/Melee/Standard/Hatchet/BoneChopper/Weapon_BoneChopper"
        },
        {
          "name": "/Items/Trinkets/Amulets/NeckboneNecklace/Amulet_NeckboneNecklace"
        },
        {
          "name": "/Items/Trinkets/Rings/FeastmastersSignet/Ring_FeastmastersSignet"
        },
        {
          "name": "/Items/Traits/Core/Glutton/Trait_Glutton",
          "coop": true
        }
      ],
      "SilverGold": [
        {
          "name": "/Items/Trinkets/Amulets/SilverRibbon/Amulet_SilverRibbon"
        },
        {
          "name": "/Items/Trinkets/Amulets/GoldenRibbon/Amulet_GoldenRibbon"
        }
      ],
      "DranGrenadier": [
        {
          "name": "/Items/Mods/Mod_Witchfire/Mod_Witchfire"
        }
      ],
      "DranOracle": [
        {
          "name": "/Items/Armor/Base/RelicTesting/QuiltedHeart/Relic_Consumable_QuiltedHeart"
        },
        {
          "name": "/Items/Traits/Core/Recovery/Trait_Recovery"
        }
      ],
      "TheHunter": [
        {
          "name": "/Items/Mods/Mod_Familiar/Mod_Familiar",
          "notes": "dream world version"
        },
        {
          "name": "/Items/Weapons/Melee/Special/HuntressSpear/Weapon_HuntressSpear"
        }
      ],
      "Rookery": [
        {
          "name": "/Items/Trinkets/Amulets/EffigyPendant/Amulet_EffigyPendant",
          "notes": "Inside lockbox"
        },
        {
          "name": "/Items/Trinkets/Amulets/CleansingStone/Amulet_CleansingStone"
        }
      ],
      "FaeArchon": [
        {
          "name": "/Items/Mods/CorrosiveRounds/Mod_CorrosiveRounds"
        }
      ],
      "FieryGraveyard": [
        {
          "name": "/Items/Trinkets/Rings/BurdenOfTheWarlock/Ring_BurdenOfTheWarlock"
        }
      ],
      "ClockTower": [
        {
          "name": "/Items/Trinkets/Rings/TimekeepersJewel/Ring_TimekeepersJewel"
        },
        {
          "name": "/Items/Mods/Mod_TimeLapse/Mod_TimeLapse"
        }
      ],
      "TownTurnedToDust": [
        {
          "name": "/Items/Trinkets/Rings/OutcastRing/Ring_OutcastRing"
        },
        {
          "name": "/Items/Trinkets/Amulets/SpiritWispAmulet/Amulet_SpiritWispAmulet"
        }
      ],
      "ThreeMenMorris": [
        {
          "name": "/Items/Armor/FaeRoyal/Armor_Head_FaeRoyalGuard"
        },
        {
          "name": "/Items/Armor/FaeRoyal/Armor_Body_FaeRoyalGuard"
        },
        {
          "name": "/Items/Armor/FaeRoyal/Armor_Legs_FaeRoyalGuard"
        },
        {
          "name": "/Items/Armor/FaeRoyal/Armor_Gloves_FaeRoyalGuard"
        },
        {
          "name": "/Items/Trinkets/Rings/GameMastersPride/Ring_GameMastersPride",
          "coop": true
        },
        {
          "name": "/Items/Weapons/Longguns/Standard/Bow/Weapon_Bow"
        }
      ],
      "RedPrince": [
        {
          "name": "/Items/Mods/Mod_Firestorm/Mod_Firestorm"
        },
        {
          "name": "/Items/Mods/Mod_BloodDraw/Mod_BloodDraw"
        },
        {
          "name": "/Items/Armor/Misc/Armor_Head_RedPrince",
          "notes": "kill with Assassins Dagger"
        }
      ],
      "NightWeaver": [
        {
          "name": "/Items/Weapons/LongGuns/Special/Nightfall/Weapon_Nightfall"
        },
        {
          "name": "/Items/Weapons/Melee/Special/Nightshade/Weapon_Nightshade"
        }
      ],
      "FaelinFaerlin": [
        {
          "name": "/Items/Weapons/LongGuns/Special/Deceit/Weapon_Deceit"
        },
        {
          "name": "/Items/Trinkets/Rings/FaelinsSigil/Ring_FaelinsSigil"
        }
      ],
      "Faerin": [
        {
          "name": "/Items/Weapons/Melee/Special/Godsplitter/Weapon_Godsplitter"
        },
        {
          "name": "/Items/Trinkets/Rings/FaerinsSigil/Ring_FaerinsSigil"
        }
      ],
      "FaeCouncil": [
        {
          "name": "/Items/Trinkets/Rings/FaeProtectorSignet/Ring_FaeProtectorSignet"
        },
        {
          "name": "/Items/Trinkets/Rings/AssassinsSeal/Ring_AssassinsSeal",
          "notes": "kill council members"
        },
        {
          "name": "/Items/Weapons/Melee/Standard/Sword/OrnateBlade/Weapon_OrnateBlade"
        }
      ],
      "AsylumHouse": [
        {
          "name": "/Items/Weapons/HandGuns/Standard/ShortBarrel/Weapon_ShortBarrel"
        },
        {
          "name": "/Items/Trinkets/Rings/AlumniRing/Ring_AlumniRing"
        }
      ],
      "Nightweb": [
        {
          "name": "/Items/Weapons/Melee/Special/Dreamcatcher/Weapon_Dreamcatcher",
          "notes": "Awarded by offering the Nightweaver Stone Doll item found in the Tormented Asylum location on Losomn to the Nightweaver's Web event found in the Tormented Asylum location on Losomn. This can be done in any mode that has rolled both locations."
        },
        {
          "name": "/Items/Armor/Base/RelicTesting/TormentedHeart/Relic_Consumable_TormentedHeart",
          "notes": "Awarded by offering the Overide Pin item found in the Timeless Horizon location on N'Erud to the Nightweaver's Web event found in the Tormented Asylum location on Losomn. This must be done on a campaign that has rolled both locations."
        },
        {
          "name": "/Items/Trinkets/Rings/RingOfRetribution/Ring_RingOfRetribution",
          "notes": "Awarded by offering the Dria's Anklet item found in the Harvester's Reach location on Losomn to the Nightweaver's Web event found in the Tormented Asylum location on Losomn. This can be done in any mode that has rolled both locations."
        },
        {
          "name": "/Items/Trinkets/Amulets/NightweaversGrudge/Amulet_NightweaversGrudge",
          "notes": "Awarded by offering the Kolkets Razor item found in The Lament location on Yaesha to the Nightweaver's Web event found in the Tormented Asylum location on Losomn. This must be done on a campaign that has rolled both locations."
        },
        {
          "name": "/Items/Weapons/HandGuns/Special/RunePistol/Weapon_RunePistol",
          "notes": "Awarded by offering the Ravenous Medallion item found in the Great Hall location on Losomn to the Nightweaver's Web event found in the Tormented Asylum location on Losomn. This can be done in any mode that has rolled both locations."
        }
      ],
      "AllFatherStory": [
        {
          "name": "/Items/Trinkets/Rings/CatalogersJewel/Ring_CatalogersJewel",
          "notes": "near entrance to The Great Sewer in Beatific Palace"
        },
        {
          "name": "/Items/Trinkets/Amulets/JestersBell/Amulet_JestersBell",
          "notes": "clap emote while Jester perfroms"
        },
        {
          "name": "/Items/Trinkets/Amulets/OneEyedJokerIdol/Amulet_OneEyedJokerIdol",
          "notes": "Jester Card Doors - face mask door"
        },
        {
          "name": "/Items/Gems/Melee/MetaGems/Misfortune/MetaGem_Misfortune",
          "notes": "Jester Card Doors - devil horns door"
        },
        {
          "name": "/Items/Armor/Base/RelicTesting/UnsulliedHeart/Relic_Consumable_UnsulliedHeart",
          "notes": "Wear OneTrueKing(AM) and both Faerin/Faelin(RI) in the Palace Courtyard"
        },
        {
          "name": "/Items/Trinkets/Amulets/ShadeBloomFloret/Amulet_ShadeBloomCrystal",
          "notes": "on the bone pile where the Jester sits in Beatific Palace"
        }
      ],
      "TheSafe": [
        {
          "name": "/Items/Trinkets/Rings/RustedHeirloom/Ring_RustedHeirloom"
        }
      ],
      "RisingTides": [
        {
          "name": "/Items/Weapons/HandGuns/Special/Meridian/Weapon_Meridian",
          "notes": "wait 90m for the water to rise"
        },
        {
          "name": "/Items/Trinkets/Rings/BurdenOfTheDivine/Ring_BurdenOfTheDivine"
        }
      ]
    },
    "Nerud": {
      "IAmLegendStory": [
        {
          "name": "/Items/Mods/StasisBeam/Mod_StasisBeam"
        }
      ],
      "TheCoreStory": [
        {
          "name": "/Items/Trinkets/Rings/DowngradedRing/Ring_DowngradedRing"
        },
        {
          "name": "/Items/Mods/EnergyWall/Mod_EnergyWall"
        },
        {
          "name": "/Items/Armor/Base/RelicTesting/VoidHeart/Relic_Consumable_VoidHeart"
        }
      ],
      "Amulet_01": [
        {
          "name": "/Items/Trinkets/Amulets/KineticShieldExchanger/Amulet_KineticShieldExchanger"
        }
      ],
      "Amulet_02": [
        {
          "name": "/Items/Trinkets/Amulets/InertOvercharger/Amulet_InertOvercharger"
        }
      ],
      "Amulet_03": [
        {
          "name": "/Items/Trinkets/Amulets/EmergencySwitch/Amulet_EmergencySwitch"
        }
      ],
      "Ring_ConservationSeal": [
        {
          "name": "/Items/Trinkets/Rings/ConservationSeal/Ring_ConservationSeal"
        }
      ],
      "Ring_DeepPocketRing": [
        {
          "name": "/Items/Trinkets/Rings/DeepPocketRing/Ring_DeepPocketRing"
        }
      ],
      "Ring_DefensiveActionLoop": [
        {
          "name": "/Items/Trinkets/Rings/DefensiveActionLoop/Ring_DefensiveActionLoop"
        }
      ],
      "Ring_FeedbackLoop": [
        {
          "name": "/Items/Trinkets/Rings/FeedbackLoop/Ring_FeedbackLoop"
        }
      ],
      "Ring_PointFocusRing": [
        {
          "name": "/Items/Trinkets/Rings/PointFocusRing/Ring_PointFocusRing"
        }
      ],
      "Ring_ReserveBoostingGem": [
        {
          "name": "/Items/Trinkets/Rings/ReserveBoostingGem/Ring_ReserveBoostingGem"
        }
      ],
      "Ring_RingOfRestocking": [
        {
          "name": "/Items/Trinkets/Rings/RingOfRestocking/Ring_RingOfRestocking"
        }
      ],
      "Ring_StoneOfExpanse": [
        {
          "name": "/Items/Trinkets/Rings/StoneOfExpanse/Ring_StoneOfExpanse"
        }
      ],
      "Ring_TargetingJewel": [
        {
          "name": "/Items/Trinkets/Rings/TargetingJewel/Ring_TargetingJewel"
        }
      ],
      "Ring_VacuumSeal": [
        {
          "name": "/Items/Trinkets/Rings/VacuumSeal/Ring_VacuumSeal"
        }
      ],
      "ElevatorShaft": [
        {
          "name": "/Items/Trinkets/Rings/PropulsionLoop/Ring_PropulsionLoop"
        },
        {
          "name": "/Items/Trinkets/Rings/LowYieldRecoveryRing/Ring_LowYieldRecoveryRing"
        }
      ],
      "RemainsBelow": [
        {
          "name": "/Items/Trinkets/Rings/ConstantVariableRing/Ring_ConstantVariableRing"
        },
        {
          "name": "/Items/Gems/Ranged/MetaGems/Timewave/MetaGem_Timewave"
        }
      ],
      "Seeker": [
        {
          "name": "/Items/Trinkets/Rings/BurdenOfTheStargazer/Ring_BurdenOfTheStargazer"
        }
      ],
      "BlackHole": [
        {
          "name": "/Items/Trinkets/Rings/RingOfDeflection/Ring_RingOfDeflection"
        },
        {
          "name": "/Items/Trinkets/Rings/FocusedJewel/Ring_FocusedJewel"
        }
      ],
      "LurkerVents": [
        {
          "name": "/Items/Trinkets/Rings/ExcessCoil/Ring_ExcessCoil"
        },
        {
          "name": "/Items/Gems/Ranged/MetaGems/Transpose/MetaGem_Transpose"
        }
      ],
      "SewageFacility": [
        {
          "name": "/Items/Trinkets/Amulets/InsulationDriver/Amulet_InsulationDriver"
        },
        {
          "name": "/Items/Trinkets/Rings/GeneratingBand/Ring_GeneratingBand",
          "notes": "Found in The Hatchery, Void Vessel Facility, Vault of the Formless, or The Putrid Domain locations on N'Erud during the Flooded Room event. Once the event starts, you will have one chance to collect the items in the room before it fills with water."
        },
        {
          "name": "/Items/Trinkets/Rings/SubterfugeLink/Ring_SubterfugeLink"
        }
      ],
      "Shockwire": [
        {
          "name": "/Items/Trinkets/Rings/BlackoutRing/Ring_BlackoutRing"
        },
        {
          "name": "/Items/Trinkets/Rings/ReroutingCable/Ring_ReroutingCable"
        }
      ],
      "StoreRoom": [
        {
          "name": "/Items/Trinkets/Rings/RingOfCrisis/Ring_RingOfCrisis"
        },
        {
          "name": "/Items/Gems/Melee/MetaGems/Disengage/MetaGem_Disengage"
        }
      ],
      "TheClaw": [
        {
          "name": "/Items/Trinkets/Rings/MomentumDriver/Ring_MomentumDriver"
        },
        {
          "name": "/Items/Weapons/Melee/Special/AtomSplitter/Weapon_AtomSplitter"
        }
      ],
      "Abomination": [
        {
          "name": "/Items/Mods/Bore/Mod_Bore"
        }
      ],
      "CustodianEye": [
        {
          "name": "/Items/Mods/PrismaticDriver/Mod_PrismaticDriver"
        }
      ],
      "Hatchery": [
        {
          "name": "/Items/Mods/SpaceCrabs/Mod_SpaceCrabs"
        }
      ],
      "Phantom": [
        {
          "name": "/Items/Trinkets/Amulets/RustedNavigatorsPendant/Amulet_RustedNavigatorsPendant"
        },
        {
          "name": "/Items/Mods/Helix/Mod_Helix"
        }
      ],
      "Extermination": [
        {
          "name": "/Quests/Quest_SideD_Extermination/Items/Quest_Item_Extermination_AICore",
          "ignore": false
        },
        {
          "name": "/Items/Trinkets/Amulets/ToxicReleaseValve/Amulet_ToxicReleaseValve"
        },
        {
          "name": "/Items/Gems/Ranged/MetaGems/Failsafe/MetaGem_Failsafe"
        },
        {
          "name": "/Items/Traits/Core/Siphoner/Trait_Siphoner"
        },
        {
          "name": "/Items/Traits/Core/Resonance/Trait_Resonance",
          "notes": "get killed by getting locked in the purge",
          "coop": true
        }
      ],
      "Extraction": [
        {
          "name": "/Items/Trinkets/Rings/GalvanizedResupplyBand/Ring_GalvanizedResupplyBand"
        },
        {
          "name": "/Items/Trinkets/Amulets/DifferenceEngine/Amulet_DifferenceEngine"
        },
        {
          "name": "/Items/Weapons/HandGuns/Special/StarShot/Weapon_StarShot"
        },
        {
          "name": "/Items/Armor/Base/RelicTesting/CrystalHeart/Relic_Consumable_CrystalHeart"
        }
      ],
      "StasisSiege": [
        {
          "name": "/Items/Trinkets/Rings/MetalDriver/Ring_MetalDriver"
        },
        {
          "name": "/Items/Weapons/HandGuns/Standard/RuptureCannon/Weapon_RuptureCannon"
        },
        {
          "name": "/Items/Traits/Core/Fitness/Trait_Fitness"
        }
      ],
      "TheDreamlessSleep": [
        {
          "name": "/Items/Armor/SpaceWorker/Armor_Head_SpaceWorker"
        },
        {
          "name": "/Items/Armor/SpaceWorker/Armor_Body_SpaceWorker"
        },
        {
          "name": "/Items/Armor/SpaceWorker/Armor_Legs_SpaceWorker"
        },
        {
          "name": "/Items/Armor/SpaceWorker/Armor_Gloves_SpaceWorker"
        },
        {
          "name": "/Items/Gems/Melee/MetaGems/Transferrence/MetaGem_Transference"
        },
        {
          "name": "/Items/Trinkets/Rings/TightlyWoundCoil/Ring_TightlyWoundCoil"
        }
      ],
      "TowerHeist": [
        {
          "name": "/Items/Trinkets/Amulets/Samoflange/Amulet_Samoflange"
        },
        {
          "name": "/Items/Trinkets/Rings/StoneOfContinuance/Ring_StoneOfContinuance"
        },
        {
          "name": "/Items/Gems/Ranged/MetaGems/Refunder/MetaGem_Refunder"
        },
        {
          "name": "/Items/Armor/Base/RelicTesting/ShieldedHeart/Relic_Consumable_ShieldedHeart"
        }
      ],
      "Train": [
        {
          "name": "/Quests/Quest_SideD_Train/Items/Quest_Item_Train_AICore",
          "ignore": false
        },
        {
          "name": "/Items/Weapons/Melee/Standard/Hammer/AtomSmasher/Weapon_AtomSmasher"
        },
        {
          "name": "/Items/Trinkets/Amulets/Hyperconductor/Amulet_Hyperconductor",
          "notes": "Found in the Terminus Station location on N'Erud, hidden in a crawlspace to the left of a ladder, in the Train event."
        },
        {
          "name": "/Items/Traits/Core/Footwork/Trait_Footwork"
        }
      ],
      "IronGiant": [
        {
          "name": "/Items/Trinkets/Rings/HardcoreMetalBand/Ring_HardcoreMetalBand"
        },
        {
          "name": "/Items/Weapons/LongGuns/Special/PlasmaCutter/Weapon_PlasmaCutter"
        }
      ],
      "OilField": [
        {
          "name": "/Items/Armor/Nerud_Pilot/Armor_Head_PilotsHelm"
        },
        {
          "name": "/Items/Trinkets/Amulets/DetonationTrigger/Amulet_DetonationTrigger"
        },
        {
          "name": "/Items/Trinkets/Rings/BlastingCapRing/Ring_BlastingCapRing"
        }
      ],
      "TheCustodian": [
        {
          "name": "/Items/Trinkets/Amulets/CoreBooster/Amulet_CoreBooster"
        },
        {
          "name": "/Items/Weapons/LongGuns/Standard/BurstRifle/Weapon_PulseRifle"
        },
        {
          "name": "/Items/Trinkets/Rings/PowerSaver/Ring_PowerSaver"
        },
        {
          "name": "/Items/Mods/Overflow/Mod_Overflow",
          "notes": "take the elevator on the right of the vending machine, now take the path on the right of the bridge and you should see the crafting material on a machine"
        },
        {
          "name": "/Items/Armor/Base/RelicTesting/SiphonHeart/Relic_Consumable_SiphonHeart",
          "notes": "give Shining Essence Echo to Custodian"
        }
      ],
      "DrzyrReplicator": [
        {
          "name": "/Items/Trinkets/Rings/MeteoriteShardRing/Ring_MeteoriteShardRing"
        },
        {
          "name": "/Items/Trinkets/Rings/Microcompressor/Ring_Microcompressor"
        },
        {
          "name": "/Items/Trinkets/Amulets/EnergyDiverter/Amulet_EnergyDiverter"
        },
        {
          "name": "/Items/Armor/Base/RelicTesting/SalvagedHeart/Relic_Consumable_SalvagedHeart"
        },
        {
          "name": "/Items/Weapons/Melee/Standard/Claws/Vice_Grips/Weapon_ViceGrips"
        },
        {
          "name": "/Items/Trinkets/Amulets/RangeFinder/Amulet_RangeFinder"
        },
        {
          "name": "/Items/Trinkets/Amulets/EffluviumEnhancer/Amulet_EffluviumEnhancer"
        },
        {
          "name": "/Items/Trinkets/Rings/BurdenOfTheMariner/Ring_BurdenOfTheMariner"
        },
        {
          "name": "/Items/Trinkets/Rings/SuppressionWard/Ring_SuppressionWard"
        },
        {
          "name": "/Items/Trinkets/Amulets/VoidIdol/Amulet_VoidIdol",
          "notes": "use Shining Essence Echo to craft at Drzyr Replicator"
        }
      ],
      "NerudGuardian": [
        {
          "name": "/Items/Weapons/LongGuns/Special/Aphelion/Weapon_Aphelion"
        },
        {
          "name": "/Items/Weapons/Melee/Special/SpectralBlade/Weapon_SpectralBlade",
          "notes": "dont put override pin"
        }
      ],
      "TalRatha": [
        {
          "name": "/Items/Weapons/HandGuns/Special/Nebula/Weapon_Nebula"
        },
        {
          "name": "/Items/Trinkets/Amulets/NavigatorsPendant/Amulet_NavigatorsPendant",
          "notes": "get eaten while wearing rusted navigators"
        },
        {
          "name": "/Items/Weapons/Melee/Special/TalRatha_Hammer/Weapon_TalRatha_Hammer",
          "notes": "get eaten by tal ratha"
        }
      ],
      "OverworldFog": [
        {
          "name": "/Items/Materials/Engrams/Item_HiddenContainer_Material_Engram_Engineer"
        },
        {
          "name": "/Items/Armor/Archetype/Engineer/Armor_Head_Engineer"
        },
        {
          "name": "/Items/Armor/Archetype/Engineer/Armor_Body_Engineer"
        },
        {
          "name": "/Items/Armor/Archetype/Engineer/Armor_Legs_Engineer"
        },
        {
          "name": "/Items/Armor/Archetype/Engineer/Armor_Gloves_Engineer"
        }
      ]
    },
    "Story": {
      "AshenWasteland": [
        {
          "name": "/Items/Armor/Archetype/Invader/Armor_Head_Invader"
        },
        {
          "name": "/Items/Armor/Archetype/Invader/Armor_Body_Invader"
        },
        {
          "name": "/Items/Armor/Archetype/Invader/Armor_Gloves_Invader"
        },
        {
          "name": "/Items/Armor/Archetype/Invader/Armor_Legs_Invader"
        },
        {
          "name": "/Items/Trinkets/Amulets/AnkhOfPower/Amulet_AnkhOfPower"
        },
        {
          "name": "/Items/Armor/Base/RelicTesting/ResonatingHeart/Relic_Consumable_ResonatingHeart"
        },
        {
          "name": "/Items/Weapons/Melee/Standard/Katana/Katana/Weapon_Katana"
        },
        {
          "name": "/Items/Trinkets/Rings/ZaniasMalice/Ring_ZaniasMalice"
        },
        {
          "name": "/Items/Trinkets/Rings/HaymakersRing/Ring_HaymakersRing"
        },
        {
          "name": "/Items/Trinkets/Rings/DyingEmber/Ring_DyingEmber"
        },
        {
          "name": "/Items/Weapons/HandGuns/Special/Hellfire/Weapon_Hellfire"
        },
        {
          "name": "/Items/Traits/Core/Handling/Trait_Handling"
        },
        {
          "name": "/Items/Trinkets/Rings/ReapingStone/Ring_ReapingStone"
        },
        {
          "name": "/Items/Mods/Mod_Defrag/Mod_Defrag"
        }
      ],
      "CorruptedHarbor": [
        {
          "name": "/Items/Trinkets/Amulets/EscalationProtocol/Amulet_EscalationProtocol"
        },
        {
          "name": "/Items/Trinkets/Rings/KineticCycleStone/Ring_KineticCycleStone"
        },
        {
          "name": "/Items/Trinkets/Rings/FlyweightsSting/Ring_FlyweightsSting"
        },
        {
          "name": "/Items/Trinkets/Rings/ProbabilityCord/Ring_ProbabilityCord"
        },
        {
          "name": "/Items/Materials/Engrams/Item_HiddenContainer_Material_Engram_Invader"
        },
        {
          "name": "/Items/Mods/Mod_Skewer/Mod_Skewer"
        },
        {
          "name": "/Items/Gems/Ranged/MetaGems/Supercharger/MetaGem_Supercharger"
        },
        {
          "name": "/Items/Armor/Base/RelicTesting/DecayedHeart/Relic_Consumable_DecayedHeart"
        },
        {
          "name": "/Items/Traits/Core/Wayfarer/Trait_Wayfarer"
        }
      ],
      "Ward13": [
        {
          "name": "/Items/Trinkets/Rings/TarnishedRing/Ring_TarnishedRing",
          "notes": "Awarded from speaking with Earl at Ward 13 and listening to his rabbit story. He can either be found sleeping in bed, or hanging on the walk way above the merchant Whispers. He will not speak to you while he sleeps, and while away, he may be resistant at first to telling you his story."
        },
        {
          "name": "/Items/Materials/Engrams/Item_HiddenContainer_Material_Engram_Medic",
          "notes": "buy Medic Pin from Norah"
        },
        {
          "name": "/Items/Weapons/LongGuns/Standard/TommyGun/Weapon_TommyGun",
          "notes": "cargo ship portal"
        },
        {
          "name": "/Items/Armor/Leto2/Armor_Head_Leto2",
          "notes": "cargo ship portal"
        },
        {
          "name": "/Items/Armor/Leto2/Armor_Body_Leto2",
          "notes": "cargo ship portal"
        },
        {
          "name": "/Items/Armor/Leto2/Armor_Gloves_Leto2",
          "notes": "cargo ship portal"
        },
        {
          "name": "/Items/Armor/Leto2/Armor_Legs_Leto2",
          "notes": "cargo ship portal"
        },
        {
          "name": "/Items/Weapons/HandGuns/Standard/SMG/Weapon_SMG",
          "notes": "cargo ship"
        },
        {
          "name": "/Items/Armor/Base/RelicTesting/RipenedHeart/Relic_Consumable_RipenedHeart",
          "notes": "thaen tree fully grown"
        },
        {
          "name": "/Items/Armor/Base/RelicTesting/LifelessHeart/Relic_Consumable_LifelessHeart",
          "notes": "eat fruit of death 3 times"
        }
      ],
      "Mudtooth": [
        {
          "name": "/Items/Materials/Engrams/Item_HiddenContainer_Material_Engram_Gunslinger",
          "notes": "Crafted by Wallace at Ward 13. Requires the Worn Cylinder item, purchased from Mudtooth at Ward 13. Available for purchase after exhausting his second set of stories."
        },
        {
          "name": "/Items/Trinkets/Amulets/GunslingersCharm/Amulet_GunslingersCharm",
          "notes": "Awarded from speaking with Mudtooth at Ward 13, and exhausting his second set of stories, in the campaign mode. The second set of stories is available to the player after completing their second biome in the campaign."
        },
        {
          "name": "/Items/Trinkets/Rings/GunslingersRing/Ring_GunslingersRing",
          "notes": "Awarded from speaking with Mudtooth at Ward 13, and exhausting his first set of stories, in the campaign mode."
        },
        {
          "name": "/Items/Materials/Engrams/Item_HiddenContainer_Material_Engram_Handler",
          "notes": "Crafted by Wallace at Ward 13. Requires the Old Whistle item, purchased from Mudtooth at Ward 13."
        }
      ],
      "Brabus": [
        {
          "name": "/Items/Materials/Engrams/Item_HiddenContainer_Material_Engram_Hunter",
          "notes": "Crafted by Wallace at Ward 13. Requires the Rusty Medal item, purchased from Brabus at Ward 13."
        },
        {
          "name": "/Items/Weapons/Handguns/Standard/HuntingPistol/Weapon_HuntingPistol"
        },
        {
          "name": "/Items/Weapons/Handguns/Standard/Magnum/Weapon_Magnum"
        },
        {
          "name": "/Items/Weapons/Handguns/Standard/Repeater/Weapon_Repeater_Rusty"
        },
        {
          "name": "/Items/Weapons/Handguns/Standard/Revolver/Weapon_Revolver"
        },
        {
          "name": "/Items/Weapons/Handguns/Standard/ServicePistol/Weapon_ServicePistol"
        },
        {
          "name": "/Items/Weapons/Longguns/Standard/AssaultRifle/Weapon_AssaultRifle"
        },
        {
          "name": "/Items/Weapons/Longguns/Standard/Coachgun/Weapon_CoachGun"
        },
        {
          "name": "/Items/Weapons/Longguns/Standard/LeverAction/Weapon_LeverAction"
        },
        {
          "name": "/Items/Weapons/Longguns/Standard/LeverAction/Weapon_LeverAction_Rusty"
        },
        {
          "name": "/Items/Weapons/Longguns/Standard/LMG/Weapon_LMG"
        },
        {
          "name": "/Items/Weapons/Melee/Standard/Hatchet/Hatchet/Weapon_Hatchet"
        },
        {
          "name": "/Items/Weapons/Melee/Standard/Flail/Flail_Steel_Base/Weapon_Flail"
        },
        {
          "name": "/Items/Weapons/Melee/Standard/GreatSword/IronGreatsword/Weapon_Greatsword"
        },
        {
          "name": "/Items/Weapons/Melee/Standard/Katana/Katana/Weapon_Katana"
        }
      ],
      "Reggie": [
        {
          "name": "/Items/Materials/Engrams/Item_HiddenContainer_Material_Engram_Challenger",
          "notes": "Crafted by Wallace at Ward 13. Requires the Old Metal Tool item, purchased from Reggie at Ward 13."
        },
        {
          "name": "/Items/Trinkets/Rings/01_Graveyard/RingOfTheAdmiral/Ring_RingOfTheAdmiral"
        },
        {
          "name": "/Items/Trinkets/Rings/PoisonStone/Ring_AcidStone"
        },
        {
          "name": "/Items/Trinkets/Rings/FireStone/Ring_FireStone"
        },
        {
          "name": "/Items/Trinkets/Rings/GroundingStone/Ring_GroundingStone"
        },
        {
          "name": "/Items/Trinkets/Amulets/ButchersFetish/Amulet_ButchersFetish",
          "notes": "Purchased from Reggie at Ward 13 after completing 5 biomes."
        },
        {
          "name": "/Items/Trinkets/Amulets/LetosAmulet/Amulet_LetosAmulet",
          "notes": "Purchased from Reggie at Ward 13 after performing a failed roll 100 times, while wearing the Leto Mark II armor set."
        },
        {
          "name": "/Items/Trinkets/Rings/BlackCatBand/Ring_BlackCatBand",
          "notes": "Purchased from Reggie at Ward 13 after dying 15 times."
        },
        {
          "name": "/Items/Trinkets/Rings/BandOfAccord/Ring_BandOfAccord",
          "notes": "Purchased from Reggie at Ward 13 after performing the High Five emote in co-op.",
          "coop": true
        },
        {
          "name": "/Items/Trinkets/Amulets/OnyxPendulum/Amulet_OnyxPendulum",
          "notes": "Purchased from Reggie at Ward 13 after completing the campaign on Nightmare difficulty."
        },
        {
          "name": "/Items/Trinkets/Amulets/NightmareSpiral/Amulet_NightmareSpiral",
          "notes": "Purchased from Reggie at Ward 13 after defeating all bosses at least once."
        },
        {
          "name": "/Items/Trinkets/Rings/BrightSteelRing/Ring_BrightSteelRing",
          "notes": "Purchased from Reggie at Ward 13 after completing 15 biomes on any difficulty."
        }
      ],
      "Cass": [
        {
          "name": "/Items/Trinkets/Rings/AmberMoonstone/Ring_AmberMoonstone",
          "notes": "Purchased from Cass at Ward 13. Merchant has a random chance to have this item in stock."
        },
        {
          "name": "/Items/Trinkets/Rings/BraidedThorns/Ring_BraidedThorns",
          "notes": "Purchased from Cass at Ward 13. Merchant has a random chance to have this item in stock."
        },
        {
          "name": "/Items/Trinkets/Rings/AkariWarBand/Ring_AkariWarBand",
          "notes": "Purchased from Cass at Ward 13. Merchant has a random chance to have this item in stock."
        },
        {
          "name": "/Items/Trinkets/Rings/CompulsionLoop/Ring_CompulsionLoop",
          "notes": "Purchased from Cass at Ward 13. Merchant has a random chance to have this item in stock."
        },
        {
          "name": "/Items/Trinkets/Rings/RockOfAnguish/Ring_RockOfAnguish",
          "notes": "Purchased from Cass at Ward 13. Merchant has a random chance to have this item in stock."
        },
        {
          "name": "/Items/Trinkets/Rings/DeceiversBand/Ring_DeceiversBand",
          "notes": "Purchased from Cass at Ward 13. Merchant has a random chance to have this item in stock."
        },
        {
          "name": "/Items/Trinkets/Rings/BlessedRing/Ring_BlessedRing",
          "notes": "Purchased from Cass at Ward 13. Merchant has a random chance to have this item in stock."
        },
        {
          "name": "/Items/Trinkets/Rings/RingOfFlawedBeauty/Ring_RingOfFlawedBeauty",
          "notes": "Purchased from Cass at Ward 13. Merchant has a random chance to have this item in stock."
        },
        {
          "name": "/Items/Trinkets/Rings/DeadKingsMemento/Ring_DeadKingsMemento",
          "notes": "Purchased from Cass at Ward 13. Merchant has a random chance to have this item in stock."
        },
        {
          "name": "/Items/Trinkets/Rings/MechanicsCog/Ring_MechanicsCog",
          "notes": "Purchased from Cass at Ward 13. Merchant has a random chance to have this item in stock."
        },
        {
          "name": "/Items/Armor/Base/RelicTesting/EnlargedHeart/Relic_Consumable_EnlargedHeart",
          "notes": "Purchased from Cass at Ward 13 after unlocking the Root Earth location in the campaign."
        },
        {
          "name": "/Items/Trinkets/Amulets/BrokenPocketWatch/Amulet_BrokenPocketWatch",
          "notes": "Purchased from Cass at Ward 13. Merchant has a random chance to have this item in stock."
        },
        {
          "name": "/Items/Trinkets/Amulets/AbrasiveWhetstone/Amulet_AbrasiveWhetstone",
          "notes": "Purchased from Cass at Ward 13. Merchant has a random chance to have this item in stock."
        },
        {
          "name": "/Items/Trinkets/Amulets/DecayedMargin/Amulet_DecayedMargin",
          "notes": "Purchased from Cass at Ward 13. Merchant has a random chance to have this item in stock."
        },
        {
          "name": "/Items/Trinkets/Amulets/TwistedIdol/Amulet_TwistedIdol",
          "notes": "Purchased from Cass at Ward 13. Merchant has a random chance to have this item in stock."
        },
        {
          "name": "/Items/Trinkets/Rings/BurdenOfTheGambler/Ring_BurdenOfTheGambler",
          "notes": "Purchased from Cass at Ward 13. Merchant has a random chance to have this item in stock."
        },
        {
          "name": "/Items/Trinkets/Rings/BurdenOfTheAudacious/Ring_BurdenOfTheAudacious",
          "notes": "Purchased from Cass at Ward 13. Merchant has a random chance to have this item in stock."
        },
        {
          "name": "/Items/Trinkets/Rings/BurdenOfTheDestroyer/Ring_BurdenOfTheDestroyer",
          "notes": "Purchased from Cass at Ward 13. Merchant has a random chance to have this item in stock."
        },
        {
          "name": "/Items/Armor/Base/RelicTesting/DivertingHeart/Relic_Consumable_DivertingHeart",
          "notes": "Purchased from Cass at Ward 13 after defeating 30 world bosses on any difficulty."
        }
      ],
      "Whispers": [
        {
          "name": "/Items/Armor/Archetype/Gunslinger/Armor_Head_Gunslinger"
        },
        {
          "name": "/Items/Armor/Archetype/Gunslinger/Armor_Body_Gunslinger"
        },
        {
          "name": "/Items/Armor/Archetype/Gunslinger/Armor_Gloves_Gunslinger"
        },
        {
          "name": "/Items/Armor/Archetype/Gunslinger/Armor_Legs_Gunslinger"
        },
        {
          "name": "/Items/Armor/Archetype_Starting/Challenger/Armor_Head_Challenger"
        },
        {
          "name": "/Items/Armor/Archetype_Starting/Challenger/Armor_Body_Challenger"
        },
        {
          "name": "/Items/Armor/Archetype_Starting/Challenger/Armor_Gloves_Challenger"
        },
        {
          "name": "/Items/Armor/Archetype_Starting/Challenger/Armor_Legs_Challenger"
        },
        {
          "name": "/Items/Armor/Archetype_Starting/Handler/Armor_Head_Handler"
        },
        {
          "name": "/Items/Armor/Archetype_Starting/Handler/Armor_Body_Handler"
        },
        {
          "name": "/Items/Armor/Archetype_Starting/Handler/Armor_Gloves_Handler"
        },
        {
          "name": "/Items/Armor/Archetype_Starting/Handler/Armor_Legs_Handler"
        },
        {
          "name": "/Items/Armor/Archetype_Starting/Hunter/Armor_Head_Hunter"
        },
        {
          "name": "/Items/Armor/Archetype_Starting/Hunter/Armor_Body_Hunter"
        },
        {
          "name": "/Items/Armor/Archetype_Starting/Hunter/Armor_Gloves_Hunter"
        },
        {
          "name": "/Items/Armor/Archetype_Starting/Hunter/Armor_Legs_Hunter"
        },
        {
          "name": "/Items/Armor/Archetype_Starting/Medic/Armor_Head_Medic"
        },
        {
          "name": "/Items/Armor/Archetype_Starting/Medic/Armor_Body_Medic"
        },
        {
          "name": "/Items/Armor/Archetype_Starting/Medic/Armor_Gloves_Medic"
        },
        {
          "name": "/Items/Armor/Archetype_Starting/Medic/Armor_Legs_Medic"
        },
        {
          "name": "/Items/Trinkets/Rings/AnastasijasInspiration/Ring_AnastasijasInspiration"
        }
      ],
      "McCabe": [
        {
          "name": "/Items/Mods/ConcussiveShot/Mod_ConcussiveShot"
        },
        {
          "name": "/Items/Mods/ScrapShot/Mod_ScrapShot"
        },
        {
          "name": "/Items/Mods/HealingShot/Mod_HealingShot"
        },
        {
          "name": "/Items/Mods/HotShot/Mod_Hotshot"
        }
      ],
      "Dwell": [
        {
          "name": "/Items/Gems/Ranged/MetaGems/Battery/MetaGem_Battery"
        },
        {
          "name": "/Items/Gems/Ranged/MetaGems/DeadlyCalm/MetaGem_DeadlyCalm"
        },
        {
          "name": "/Items/Gems/Melee/MetaGems/Dervish/MetaGem_Dervish"
        },
        {
          "name": "/Items/Gems/Ranged/MetaGems/Feedback/MetaGem_Feedback"
        },
        {
          "name": "/Items/Gems/Ranged/MetaGems/Harmonizer/MetaGem_Harmonizer"
        },
        {
          "name": "/Items/Gems/Melee/MetaGems/Resentment/MetaGem_Resentment"
        },
        {
          "name": "/Items/Gems/Melee/MetaGems/ShieldBreaker/MetaGem_ShieldBreaker"
        },
        {
          "name": "/Items/Gems/Ranged/MetaGems/Slayer/MetaGem_Slayer"
        },
        {
          "name": "/Items/Gems/Melee/MetaGems/WeaponLord/MetaGem_WeaponLord"
        }
      ],
      "Labyrinth": [
        {
          "name": "/Items/Trinkets/Rings/DenseSiliconRing/Ring_DenseSiliconRing"
        },
        {
          "name": "/Items/Trinkets/Rings/ShardBandedRing/Ring_ShardBandedRing"
        },
        {
          "name": "/Items/Trinkets/Rings/EncryptedLoop/Ring_EncryptedLoop"
        },
        {
          "name": "/Items/Trinkets/Amulets/EnergizedNeckCoil/Amulet_EnergizedNeckCoil"
        },
        {
          "name": "/Items/Weapons/HandGuns/Special/Enigma/Weapon_Enigma"
        },
        {
          "name": "/Items/Weapons/HandGuns/Special/CubeGun/Weapon_CubeGun"
        },
        {
          "name": "/Items/Weapons/Melee/Special/LabyrinthStaff/Weapon_LabyrinthStaff"
        },
        {
          "name": "/Items/Gems/Melee/MetaGems/VengefulStrike/MetaGem_VengefulStrike"
        },
        {
          "name": "/Items/Armor/Base/RelicTesting/ReprocessedHeart/Relic_Consumable_ReprocessedHeart"
        },
        {
          "name": "/Items/Armor/Base/RelicTesting/RunedHeart/Relic_Consumable_RunedHeart"
        },
        {
          "name": "/Items/Traits/Archetype/Amplitude/Trait_Amplitude"
        }
      ],
      "LabyrinthBackrooms": [
        {
          "name": "/Items/Trinkets/Amulets/GunfireSecurityLanyard/Amulet_GunfireSecurityLanyard"
        },
        {
          "name": "/Items/Trinkets/Rings/BisectedRing/Ring_BisectedRing"
        },
        {
          "name": "/Items/Materials/Engrams/Item_HiddenContainer_Material_Engram_Archon"
        }
      ]
    },
    "Uncategorized": {
      "Uncategorized": [
        {
          "name": "/Items/Armor/Archetype/Arcanist/Armor_Head_Archon"
        },
        {
          "name": "/Items/Armor/Archetype/Arcanist/Armor_Body_Archon"
        },
        {
          "name": "/Items/Armor/Archetype/Arcanist/Armor_Gloves_Archon"
        },
        {
          "name": "/Items/Armor/Archetype/Arcanist/Armor_Legs_Archon"
        },
        {
          "name": "/Items/Armor/Archetype/Explorer/Armor_Head_Explorer"
        },
        {
          "name": "/Items/Armor/Archetype/Explorer/Armor_Body_Explorer"
        },
        {
          "name": "/Items/Armor/Archetype/Explorer/Armor_Gloves_Explorer"
        },
        {
          "name": "/Items/Armor/Archetype/Explorer/Armor_Legs_Explorer"
        },
        {
          "name": "/Items/Traits/Archetype/AmmoReserves/Trait_AmmoReserves"
        },
        {
          "name": "/Items/Traits/Archetype/Amplitude/Trait_Amplitude"
        },
        {
          "name": "/Items/Traits/Archetype/FlashCaster/Trait_FlashCaster",
          "notes": "Unlocked automatically after leveling up the Archon archetype once."
        },
        {
          "name": "/Items/Traits/Archetype/Fortify/Trait_Fortify"
        },
        {
          "name": "/Items/Traits/Archetype/Kinship/Trait_Kinship",
          "notes": "Unlocked automatically after leveling up the Handler archetype once."
        },
        {
          "name": "/Items/Traits/Archetype/Longshot/Trait_Longshot",
          "notes": "Unlocked automatically after leveling up the Hunter archetype once."
        },
        {
          "name": "/Items/Traits/Archetype/Potency/Trait_Potency",
          "notes": "Unlocked automatically after leveling up the Alchemist archetype once."
        },
        {
          "name": "/Items/Traits/Archetype/Regrowth/Trait_Regrowth"
        },
        {
          "name": "/Items/Traits/Archetype/StrongBack/Trait_StrongBack",
          "notes": "Unlocked automatically after leveling up the Challenger archetype once."
        },
        {
          "name": "/Items/Traits/Archetype/Swiftness/Trait_Swiftness"
        },
        {
          "name": "/Items/Traits/Archetype/Triage/Trait_Triage"
        },
        {
          "name": "/Items/Traits/Archetype/Untouchable/Trait_Untouchable",
          "notes": "Unlocked automatically after leveling up the Invader archetype once."

        },
        {
          "name": "/Items/Traits/Core/Vigor/Trait_Vigor"
        },
        {
          "name": "/Items/Traits/Core/Endurance/Trait_Endurance"
        },
        {
          "name": "/Items/Traits/Core/Spirit/Trait_Spirit"
        },
        {
          "name": "/Items/Traits/Core/Expertise/Trait_Expertise"
        },
        {
          "name": "/Items/Traits/Core/Revivalist/Trait_Revivalist",
          "notes": "Unlocked automatically after reviving a teammate 15 times.",
          "coop": true
        },
        {
          "name": "/Items/Traits/Core/Scholar/Trait_Scholar",
          "notes": "Unlocked automatically after defeating the Annihilation Boss on any difficulty."
        },
        {
          "name": "/Items/Trinkets/Rings/PanMageSigil/Ring_PanMageSigil",
          "notes": "Purchased from Reggie at Ward 13 after defeating a Yaesha World Boss on any difficulty in the Hardcore mode.",
          "mode": "Hardcore"
        },
        {
          "name": "/Items/Trinkets/Rings/DranScavengerSigil/Ring_DranScavengerSigil",
          "notes": "Purchased from Reggie at Ward 13 after defeating a Losomn World Boss on any difficulty in the Hardcore mode.",
          "mode": "Hardcore"
        },
        {
          "name": "/Items/Trinkets/Rings/DrzyrSniperSigil/Ring_DrzyrSniperSigil",
          "notes": "Purchased from Reggie at Ward 13 after defeating a N'Erud World Boss on any difficulty in the Hardcore mode.",
          "mode": "Hardcore"
        },
        {
          "name": "/Items/Trinkets/Rings/02_OnHold/ProvisionerRing/Ring_ProvisionerRing",
          "notes": "Purchased from Reggie at Ward 13 after defeating the Labyrinth Sentinel on any difficulty in the Hardcore mode.",
          "mode": "Hardcore"
        },
        {
          "name": "/Items/Trinkets/Amulets/DaredevilsCharm/Amulet_DaredevilsCharm",
          "notes": "Purchased from Reggie at Ward 13 after completing the campaign on any difficulty in the Hardcore mode.",
          "mode": "Hardcore"
        },
        {
          "name": "/Items/Weapons/Longguns/Special/Sporebloom/Weapon_Sporebloom",
          "notes": "Purchased from Brabus at Ward 13 after completing the campaign on Veteran difficulty."
        },
        {
          "name": "/Items/Weapons/Longguns/Special/Starkiller/Weapon_Starkiller",
          "notes": "Purchased from Brabus at Ward 13 after completing the campaign on any difficulty in the Hardcore mode.",
          "mode": "Hardcore"
        },
        {
          "name": "/Items/Weapons/Longguns/Special/Savior/Weapon_Savior",
          "notes": "Purchased from Brabus at Ward 13 after completing the campaign on Veteran difficulty in the Hardcore mode.",
          "mode": "Hardcore"
        },
        {
          "name": "/Items/Weapons/Melee/Special/HerosSword/Weapon_HerosSword",
          "notes": "Purchased from Brabus at Ward 13 after completing the campaign on Nightmare difficulty."
        },
        {
          "name": "/Items/Weapons/Melee/Special/Smolder/Weapon_Smolder",
          "notes": "Purchased from Brabus at Ward 13 after completing the campaign on Veteran difficulty."
        },
        {
          "name": "/Items/Weapons/Melee/Special/WorldsEdge/Weapon_WorldsEdge",
          "notes": "Purchased from Brabus at Ward 13 after completing the campaign on Apocalypse difficulty."
        }
      ]
    }
  }
}
